flightradar_client/__init__.py
flightradar_client/__version__.py
flightradar_client/consts.py
flightradar_client/dump1090_aircrafts.py
flightradar_client/exceptions.py
flightradar_client/feed.py
flightradar_client/feed_aggregator.py
flightradar_client/feed_entry.py
flightradar_client/feed_manager.py
flightradar_client/fr24feed_flights.py
flightradar_client/statistics.py
flightradar_client/utils.py
flightradar_client-0.9.dist-info/LICENSE
flightradar_client-0.9.dist-info/METADATA
flightradar_client-0.9.dist-info/WHEEL
flightradar_client-0.9.dist-info/top_level.txt
flightradar_client-0.9.dist-info/RECORD
