Metadata-Version: 2.1
Name: flightradar-client
Version: 0.9
Summary: Flightradar client library.
Home-page: https://github.com/exxamalte/python-flightradar-client
Author: Malte Franken
Author-email: coding@subspace.de
License: Apache-2.0
Platform: UNKNOWN
Classifier: Programming Language :: Python :: 3.7
Classifier: Programming Language :: Python :: 3.8
Classifier: Programming Language :: Python :: 3.9
Classifier: Programming Language :: Python :: 3.10
Classifier: Programming Language :: Python :: 3.11
Classifier: License :: OSI Approved :: Apache Software License
Classifier: Operating System :: OS Independent
Requires-Dist: haversine (>=2.7.0)
Requires-Dist: aiohttp (<4,>=3.7.4)
Requires-Dist: async-timeout
